LICENSE
MANIFEST.in
README.rst
setup.cfg
setup.py
versioneer.py
stretch/__init__.py
stretch/_version.py
stretch/stretch.py
stretch.egg-info/PKG-INFO
stretch.egg-info/SOURCES.txt
stretch.egg-info/dependency_links.txt
stretch.egg-info/entry_points.txt
stretch.egg-info/top_level.txt