Metadata-Version: 1.1
Name: stretch
Version: 1.4
Summary: PBKDF2 on the command line
Home-page: https://github.com/felipedau/stretch
Author: Felipe Dau
Author-email: dau.felipe@gmail.com
License: MIT
Keywords: PBKDF2 key derivation function password stretching
Platform: UNKNOWN
Classifier: Development Status :: 4 - Beta
Classifier: Environment :: Console
Classifier: Intended Audience :: Developers
Classifier: Intended Audience :: End Users/Desktop
Classifier: License :: OSI Approved :: MIT License
Classifier: Operating System :: POSIX :: Linux
Classifier: Programming Language :: Python :: 2.7
Classifier: Topic :: Security :: Cryptography
